min_vec/__init__.py
min_vec/api.py
min_vec/authorize.py
min_vec/config.py
min_vec/engines.py
min_vec/fields_mapper.py
min_vec/filter.py
min_vec/ivf_index.py
min_vec/kmeans.py
min_vec/matrix_serializer.py
min_vec/query.py
min_vec/scaler.py
min_vec/session.py
min_vec/storage.py
min_vec/utils.py
min_vec/api/__init__.py
min_vec/api/api.py
min_vec/api/client_api.py
min_vec/api/high_level.py
min_vec/api/http_api.py
min_vec/api/low_level.py
min_vec/api/http_api/__init__.py
min_vec/api/http_api/client_api.py
min_vec/api/http_api/heartbeat.py
min_vec/api/http_api/http_api.py
min_vec/api/native_api/__init__.py
min_vec/api/native_api/high_level.py
min_vec/api/native_api/low_level.py
min_vec/computational_layer/__init__.py
min_vec/computational_layer/engines.py
min_vec/configs/__init__.py
min_vec/configs/config.py
min_vec/configs/parameters_validator.py
min_vec/core_components/__init__.py
min_vec/core_components/counter.py
min_vec/core_components/cross_lock.py
min_vec/core_components/fields_filter.py
min_vec/core_components/filter.py
min_vec/core_components/id_checker.py
min_vec/core_components/kmeans.py
min_vec/core_components/kv_cache_index.py
min_vec/core_components/limited_dict.py
min_vec/core_components/limited_sort.py
min_vec/core_components/metadata_kv.py
min_vec/core_components/scaler.py
min_vec/core_components/thread_safe_list.py
min_vec/data_structures/__init__.py
min_vec/data_structures/fields_mapper.py
min_vec/data_structures/filter.py
min_vec/data_structures/kmeans.py
min_vec/data_structures/limited_dict.py
min_vec/data_structures/limited_sort.py
min_vec/data_structures/scaler.py
min_vec/execution_layer/__init__.py
min_vec/execution_layer/cluster_worker.py
min_vec/execution_layer/matrix_serializer.py
min_vec/execution_layer/query.py
min_vec/execution_layer/session.py
min_vec/storage_layer/__init__.py
min_vec/storage_layer/storage.py
min_vec/structures/__init__.py
min_vec/structures/counter.py
min_vec/structures/fields_filter.py
min_vec/structures/filter.py
MinVectorDB-0.3.5.dist-info/LICENSE
MinVectorDB-0.3.5.dist-info/METADATA
MinVectorDB-0.3.5.dist-info/WHEEL
MinVectorDB-0.3.5.dist-info/entry_points.txt
MinVectorDB-0.3.5.dist-info/top_level.txt
MinVectorDB-0.3.5.dist-info/RECORD
